[
    {
        "frame_count": "1",
        "time": "21:26:47.528548",
        "data": [],
        "ids": []
    },
    {
        "frame_count": "2",
        "time": "21:26:47.977356",
        "data": [],
        "ids": []
    },
    {
        "frame_count": "3",
        "time": "21:26:48.207591",
        "data": [],
        "ids": []
    },
    {
        "frame_count": "4",
        "time": "21:26:48.431588",
        "data": [],
        "ids": []
    },
    {
        "frame_count": "5",
        "time": "21:26:48.670955",
        "data": [],
        "ids": []
    },
    {
        "frame_count": "6",
        "time": "21:26:48.905630",
        "data": [],
        "ids": []
    },
    {
        "frame_count": "7",
        "time": "21:26:49.265277",
        "data": [],
        "ids": []
    },
    {
        "frame_count": "8",
        "time": "21:26:49.519719",
        "data": [],
        "ids": []
    },
    {
        "frame_count": "9",
        "time": "21:26:49.792454",
        "data": [],
        "ids": []
    },
    {
        "frame_count": "10",
        "time": "21:26:50.045648",
        "data": [],
        "ids": []
    },
    {
        "frame_count": "11",
        "time": "21:26:50.311893",
        "data": [],
        "ids": []
    },
    {
        "frame_count": "12",
        "time": "21:26:50.575281",
        "data": [],
        "ids": []
    },
    {
        "frame_count": "13",
        "time": "21:26:51.271721",
        "data": [],
        "ids": []
    },
    {
        "frame_count": "14",
        "time": "21:26:51.721182",
        "data": [],
        "ids": []
    },
    {
        "frame_count": "15",
        "time": "21:26:51.978441",
        "data": [],
        "ids": []
    },
    {
        "frame_count": "16",
        "time": "21:26:52.233679",
        "data": [
            {
                "x1": "250.80520775402576",
                "x2": "266.97993355607844",
                "id": "33.0",
                "y1": "43.97383172786938",
                "y2": "68.2871070157033"
            }
        ],
        "ids": [
            "33.0"
        ]
    },
    {
        "frame_count": "17",
        "time": "21:26:52.488636",
        "data": [
            {
                "x1": "255.7860295317061",
                "x2": "273.1859587123318",
                "id": "33.0",
                "y1": "42.24299543567159",
                "y2": "66.25793030536084"
            }
        ],
        "ids": [
            "33.0"
        ]
    },
    {
        "frame_count": "18",
        "time": "21:26:52.734619",
        "data": [
            {
                "x1": "262.650329171606",
                "x2": "274.4946883392769",
                "id": "34.0",
                "y1": "17.365903277032515",
                "y2": "36.335730532815525"
            },
            {
                "x1": "264.7673745831876",
                "x2": "278.9563939823446",
                "id": "33.0",
                "y1": "41.48001830761292",
                "y2": "64.48959738106437"
            }
        ],
        "ids": [
            "34.0",
            "33.0"
        ]
    },
    {
        "frame_count": "19",
        "time": "21:26:52.982522",
        "data": [
            {
                "x1": "272.2032397744089",
                "x2": "289.4645065427689",
                "id": "33.0",
                "y1": "38.86848168075047",
                "y2": "63.52487060116663"
            }
        ],
        "ids": [
            "33.0"
        ]
    },
    {
        "frame_count": "20",
        "time": "21:26:53.225487",
        "data": [
            {
                "x1": "275.1687596507685",
                "x2": "293.5793294362861",
                "id": "33.0",
                "y1": "38.13752909267939",
                "y2": "63.13047590339839"
            }
        ],
        "ids": [
            "33.0"
        ]
    },
    {
        "frame_count": "21",
        "time": "21:26:53.471507",
        "data": [
            {
                "x1": "282.46908669253094",
                "x2": "299.8949745093637",
                "id": "33.0",
                "y1": "37.69281532557859",
                "y2": "62.60773015262757"
            }
        ],
        "ids": [
            "33.0"
        ]
    },
    {
        "frame_count": "22",
        "time": "21:26:53.713589",
        "data": [
            {
                "x1": "288.8854694731267",
                "x2": "308.0902894775062",
                "id": "33.0",
                "y1": "36.69720421431661",
                "y2": "62.676654620686946"
            }
        ],
        "ids": [
            "33.0"
        ]
    },
    {
        "frame_count": "23",
        "time": "21:26:53.951232",
        "data": [
            {
                "x1": "294.46240559720513",
                "x2": "312.764480411166",
                "id": "33.0",
                "y1": "35.49922346386216",
                "y2": "60.93354242432208"
            }
        ],
        "ids": [
            "33.0"
        ]
    },
    {
        "frame_count": "24",
        "time": "21:26:54.205934",
        "data": [
            {
                "x1": "303.59317770207934",
                "x2": "322.3075472599547",
                "id": "33.0",
                "y1": "34.09410269882801",
                "y2": "59.99247494658337"
            }
        ],
        "ids": [
            "33.0"
        ]
    },
    {
        "frame_count": "25",
        "time": "21:26:54.445807",
        "data": [
            {
                "x1": "309.3932716209097",
                "x2": "328.314110470173",
                "id": "33.0",
                "y1": "33.8847570200863",
                "y2": "59.40941494466604"
            }
        ],
        "ids": [
            "33.0"
        ]
    },
    {
        "frame_count": "26",
        "time": "21:26:54.686869",
        "data": [
            {
                "x1": "316.5138833887585",
                "x2": "333.07770010539184",
                "id": "33.0",
                "y1": "36.79715544795775",
                "y2": "60.255347847312606"
            }
        ],
        "ids": [
            "33.0"
        ]
    },
    {
        "frame_count": "27",
        "time": "21:26:54.933362",
        "data": [
            {
                "x1": "324.10120051708617",
                "x2": "343.35594207664263",
                "id": "33.0",
                "y1": "23.362762707819716",
                "y2": "54.028415454648496"
            }
        ],
        "ids": [
            "33.0"
        ]
    },
    {
        "frame_count": "28",
        "time": "21:26:55.191300",
        "data": [
            {
                "x1": "72.93448403651021",
                "x2": "162.19426447810739",
                "id": "52.0",
                "y1": "513.6258467288362",
                "y2": "564.3180701272454"
            },
            {
                "x1": "328.1045306117577",
                "x2": "348.90872244018476",
                "id": "33.0",
                "y1": "16.579128001719127",
                "y2": "52.82087017936796"
            }
        ],
        "ids": [
            "52.0",
            "33.0"
        ]
    },
    {
        "frame_count": "29",
        "time": "21:26:55.436000",
        "data": [
            {
                "x1": "79.90564091553858",
                "x2": "170.08806301694756",
                "id": "52.0",
                "y1": "496.1840836673712",
                "y2": "549.3272835441096"
            }
        ],
        "ids": [
            "52.0"
        ]
    },
    {
        "frame_count": "30",
        "time": "21:26:55.677746",
        "data": [
            {
                "x1": "85.05590957392366",
                "x2": "172.798419331753",
                "id": "52.0",
                "y1": "472.9636614692606",
                "y2": "525.1171593209158"
            }
        ],
        "ids": [
            "52.0"
        ]
    },
    {
        "frame_count": "31",
        "time": "21:26:55.940466",
        "data": [
            {
                "x1": "91.78854289639644",
                "x2": "176.775924356781",
                "id": "52.0",
                "y1": "452.9216420971975",
                "y2": "506.81133935841444"
            }
        ],
        "ids": [
            "52.0"
        ]
    },
    {
        "frame_count": "32",
        "time": "21:26:56.193265",
        "data": [
            {
                "x1": "100.58086965305338",
                "x2": "185.2196117661156",
                "id": "52.0",
                "y1": "429.4301640706615",
                "y2": "481.7664870640839"
            }
        ],
        "ids": [
            "52.0"
        ]
    },
    {
        "frame_count": "33",
        "time": "21:26:56.467919",
        "data": [
            {
                "x1": "19.53342236909156",
                "x2": "44.2866056412874",
                "id": "59.0",
                "y1": "192.70517825090573",
                "y2": "217.83187039288734"
            },
            {
                "x1": "115.37344285831588",
                "x2": "198.79240231214774",
                "id": "52.0",
                "y1": "404.0773187570887",
                "y2": "459.22485855041936"
            }
        ],
        "ids": [
            "59.0",
            "52.0"
        ]
    },
    {
        "frame_count": "34",
        "time": "21:26:56.713514",
        "data": [
            {
                "x1": "34.82214160540776",
                "x2": "49.4835636853059",
                "id": "63.0",
                "y1": "258.05851131149456",
                "y2": "277.6894182189488"
            },
            {
                "x1": "23.15522892787115",
                "x2": "49.61548561354762",
                "id": "59.0",
                "y1": "186.4620843055247",
                "y2": "212.59398118537237"
            },
            {
                "x1": "130.4246140081113",
                "x2": "206.45922291125072",
                "id": "52.0",
                "y1": "377.64953334782956",
                "y2": "430.6083378420319"
            }
        ],
        "ids": [
            "63.0",
            "59.0",
            "52.0"
        ]
    },
    {
        "frame_count": "1",
        "time": "21:27:03.956415",
        "data": [],
        "ids": []
    },
    {
        "frame_count": "1",
        "time": "21:28:35.853878",
        "data": [],
        "ids": []
    },
    {
        "frame_count": "1",
        "time": "21:29:37.993810",
        "data": [],
        "ids": []
    },
    {
        "frame_count": "1",
        "time": "21:30:34.297246",
        "ids": [],
        "data": []
    },
    {
        "frame_count": "2",
        "time": "21:30:34.751293",
        "data": [],
        "ids": []
    },
    {
        "frame_count": "3",
        "time": "21:30:34.977834",
        "ids": [],
        "data": []
    },
    {
        "frame_count": "4",
        "time": "21:30:35.208263",
        "data": [],
        "ids": []
    },
    {
        "frame_count": "5",
        "time": "21:30:35.443263",
        "ids": [],
        "data": []
    },
    {
        "frame_count": "6",
        "time": "21:30:35.685289",
        "data": [],
        "ids": []
    },
    {
        "frame_count": "7",
        "time": "21:30:36.048453",
        "ids": [],
        "data": []
    },
    {
        "frame_count": "8",
        "time": "21:30:36.310031",
        "data": [],
        "ids": []
    },
    {
        "frame_count": "9",
        "time": "21:30:36.570209",
        "ids": [],
        "data": []
    },
    {
        "frame_count": "10",
        "time": "21:30:36.830357",
        "data": [],
        "ids": []
    },
    {
        "frame_count": "11",
        "time": "21:30:37.072457",
        "ids": [],
        "data": []
    },
    {
        "frame_count": "12",
        "time": "21:30:37.340313",
        "data": [],
        "ids": []
    },
    {
        "frame_count": "13",
        "time": "21:30:37.599627",
        "ids": [],
        "data": []
    },
    {
        "frame_count": "14",
        "time": "21:30:37.852932",
        "data": [],
        "ids": []
    },
    {
        "frame_count": "15",
        "time": "21:30:38.117236",
        "ids": [],
        "data": []
    },
    {
        "frame_count": "16",
        "time": "21:30:38.359140",
        "data": [
            {
                "x1": "250.80520775402576",
                "x2": "266.97993355607844",
                "id": "33.0",
                "y1": "43.97383172786938",
                "y2": "68.2871070157033"
            }
        ],
        "ids": [
            "33.0"
        ]
    },
    {
        "frame_count": "17",
        "time": "21:30:38.597901",
        "ids": [
            "33.0"
        ],
        "data": [
            {
                "x1": "255.7860295317061",
                "x2": "273.1859587123318",
                "y1": "42.24299543567159",
                "id": "33.0",
                "y2": "66.25793030536084"
            }
        ]
    },
    {
        "frame_count": "18",
        "time": "21:30:38.835350",
        "data": [
            {
                "x1": "262.650329171606",
                "x2": "274.4946883392769",
                "id": "34.0",
                "y1": "17.365903277032515",
                "y2": "36.335730532815525"
            },
            {
                "x1": "264.7673745831876",
                "x2": "278.9563939823446",
                "id": "33.0",
                "y1": "41.48001830761292",
                "y2": "64.48959738106437"
            }
        ],
        "ids": [
            "34.0",
            "33.0"
        ]
    },
    {
        "frame_count": "19",
        "time": "21:30:39.072660",
        "ids": [
            "33.0"
        ],
        "data": [
            {
                "x1": "272.2032397744089",
                "x2": "289.4645065427689",
                "y1": "38.86848168075047",
                "id": "33.0",
                "y2": "63.52487060116663"
            }
        ]
    },
    {
        "frame_count": "20",
        "time": "21:30:39.337397",
        "data": [
            {
                "x1": "275.1687596507685",
                "x2": "293.5793294362861",
                "id": "33.0",
                "y1": "38.13752909267939",
                "y2": "63.13047590339839"
            }
        ],
        "ids": [
            "33.0"
        ]
    },
    {
        "frame_count": "21",
        "time": "21:30:39.585819",
        "ids": [
            "33.0"
        ],
        "data": [
            {
                "x1": "282.46908669253094",
                "x2": "299.8949745093637",
                "y1": "37.69281532557859",
                "id": "33.0",
                "y2": "62.60773015262757"
            }
        ]
    },
    {
        "frame_count": "22",
        "time": "21:30:39.836513",
        "data": [
            {
                "x1": "288.8854694731267",
                "x2": "308.0902894775062",
                "id": "33.0",
                "y1": "36.69720421431661",
                "y2": "62.676654620686946"
            }
        ],
        "ids": [
            "33.0"
        ]
    },
    {
        "frame_count": "23",
        "time": "21:30:40.087961",
        "ids": [
            "33.0"
        ],
        "data": [
            {
                "x1": "294.46240559720513",
                "x2": "312.764480411166",
                "y1": "35.49922346386216",
                "id": "33.0",
                "y2": "60.93354242432208"
            }
        ]
    },
    {
        "frame_count": "24",
        "time": "21:30:40.344382",
        "data": [
            {
                "x1": "303.59317770207934",
                "x2": "322.3075472599547",
                "id": "33.0",
                "y1": "34.09410269882801",
                "y2": "59.99247494658337"
            }
        ],
        "ids": [
            "33.0"
        ]
    },
    {
        "frame_count": "25",
        "time": "21:30:40.595284",
        "ids": [
            "33.0"
        ],
        "data": [
            {
                "x1": "309.3932716209097",
                "x2": "328.314110470173",
                "y1": "33.8847570200863",
                "id": "33.0",
                "y2": "59.40941494466604"
            }
        ]
    },
    {
        "frame_count": "26",
        "time": "21:30:41.226080",
        "data": [
            {
                "x1": "316.5138833887585",
                "x2": "333.07770010539184",
                "id": "33.0",
                "y1": "36.79715544795775",
                "y2": "60.255347847312606"
            }
        ],
        "ids": [
            "33.0"
        ]
    },
    {
        "frame_count": "27",
        "time": "21:30:41.720982",
        "ids": [
            "33.0"
        ],
        "data": [
            {
                "x1": "324.10120051708617",
                "x2": "343.35594207664263",
                "y1": "23.362762707819716",
                "id": "33.0",
                "y2": "54.028415454648496"
            }
        ]
    },
    {
        "frame_count": "28",
        "time": "21:30:41.964280",
        "data": [
            {
                "x1": "72.93448403651021",
                "x2": "162.19426447810739",
                "id": "52.0",
                "y1": "513.6258467288362",
                "y2": "564.3180701272454"
            },
            {
                "x1": "328.1045306117577",
                "x2": "348.90872244018476",
                "id": "33.0",
                "y1": "16.579128001719127",
                "y2": "52.82087017936796"
            }
        ],
        "ids": [
            "52.0",
            "33.0"
        ]
    },
    {
        "frame_count": "29",
        "time": "21:30:42.209084",
        "ids": [
            "52.0"
        ],
        "data": [
            {
                "x1": "79.90564091553858",
                "x2": "170.08806301694756",
                "y1": "496.1840836673712",
                "id": "52.0",
                "y2": "549.3272835441096"
            }
        ]
    },
    {
        "frame_count": "30",
        "time": "21:30:42.464394",
        "data": [
            {
                "x1": "85.05590957392366",
                "x2": "172.798419331753",
                "id": "52.0",
                "y1": "472.9636614692606",
                "y2": "525.1171593209158"
            }
        ],
        "ids": [
            "52.0"
        ]
    },
    {
        "frame_count": "31",
        "time": "21:30:42.710396",
        "ids": [
            "52.0"
        ],
        "data": [
            {
                "x1": "91.78854289639644",
                "x2": "176.775924356781",
                "y1": "452.9216420971975",
                "id": "52.0",
                "y2": "506.81133935841444"
            }
        ]
    },
    {
        "frame_count": "32",
        "time": "21:30:42.954672",
        "data": [
            {
                "x1": "100.58086965305338",
                "x2": "185.2196117661156",
                "id": "52.0",
                "y1": "429.4301640706615",
                "y2": "481.7664870640839"
            }
        ],
        "ids": [
            "52.0"
        ]
    },
    {
        "frame_count": "33",
        "time": "21:30:43.201679",
        "ids": [
            "59.0",
            "52.0"
        ],
        "data": [
            {
                "x1": "19.53342236909156",
                "x2": "44.2866056412874",
                "y1": "192.70517825090573",
                "id": "59.0",
                "y2": "217.83187039288734"
            },
            {
                "x1": "115.37344285831588",
                "x2": "198.79240231214774",
                "y1": "404.0773187570887",
                "id": "52.0",
                "y2": "459.22485855041936"
            }
        ]
    },
    {
        "frame_count": "34",
        "time": "21:30:43.458707",
        "data": [
            {
                "x1": "34.82214160540776",
                "x2": "49.4835636853059",
                "id": "63.0",
                "y1": "258.05851131149456",
                "y2": "277.6894182189488"
            },
            {
                "x1": "23.15522892787115",
                "x2": "49.61548561354762",
                "id": "59.0",
                "y1": "186.4620843055247",
                "y2": "212.59398118537237"
            },
            {
                "x1": "130.4246140081113",
                "x2": "206.45922291125072",
                "id": "52.0",
                "y1": "377.64953334782956",
                "y2": "430.6083378420319"
            }
        ],
        "ids": [
            "63.0",
            "59.0",
            "52.0"
        ]
    },
    {
        "frame_count": "35",
        "time": "21:30:43.703102",
        "ids": [
            "67.0",
            "63.0",
            "59.0",
            "52.0"
        ],
        "data": [
            {
                "x1": "378.35671526035276",
                "x2": "396.0295685838595",
                "y1": "25.048250022920893",
                "id": "67.0",
                "y2": "58.09130262792401"
            },
            {
                "x1": "34.93065114796184",
                "x2": "49.60361638090191",
                "y1": "257.63805614813464",
                "id": "63.0",
                "y2": "276.8753227013831"
            },
            {
                "x1": "26.933075615398934",
                "x2": "52.04562648175596",
                "y1": "181.15578412643967",
                "id": "59.0",
                "y2": "206.62044125710108"
            },
            {
                "x1": "144.8224112672732",
                "x2": "215.98486246496287",
                "y1": "355.80162224433985",
                "id": "52.0",
                "y2": "408.3513009029303"
            }
        ]
    }
]